Workbook

Sheet Sheet1
A1: Financial Modeling and Financial Statement Analysis of Blackstone Inc. | E1: Historical Data
A2: Using Blackstone Annual Report 2025 (FY 2024)
A4: Particulars | B4: 2022 | C4: 2023 | D4: 2024
A5: Total Revenue | B5: 8517673 | C5: 8022841 | D5: 13229968
A6: Net Income | B6: 2988909 | C6: 2444253 | D6: 5437809
A7: Total Assets | B7: — | C7: 40287530 | D7: 43469875
A8: Total Liabilities | B8: — | C8: 22277258 | D8: 23794860
A9: Total Equity | B9: — | C9: 16896141 | D9: 18693616
A10: Operating Cash Flow (Net Cash Provided by Operating Activities) | B10: 6336253 | C10: 4056906 | D10: 3481662
A11: Capital Expenditure (Purchase of Furniture, Equipment and Leasehold Improvements) | B11: 235497 | C11: 224231 | D11: 61409
A13: Revenue Growth(%) | B13: =B6/B5 -> 0.35090676 | C13: =(C5-B5)/B5 -> -0.05809474 | D13: =(D5-C5)/C5 -> 0.64903779
A14: Net Profit Margin(%) | B14: — | C14: =C6/C5 -> 0.30466178 | D14: =D6/D5 -> 0.41102208
A15: ROA(%) | B15: — | C15: =C6/C7 -> 0.060670212 | D15: =D6/D7 -> 0.12509373
A16: ROE(%) | B16: — | C16: =C6/C9 -> 0.14466339 | D16: =D6/D9 -> 0.29089123

Sheet Forecast Model
A4: Particulars | B4: 2022 | C4: 2023 | D4: 2024 | E4: 2025E | F4: 2026E | G4: 2027E
A5: Total Revenue | B5: =Sheet1!B5 -> 8517673 | C5: =Sheet1!C5 -> 8022841 | D5: =Sheet1!D5 -> 13229968 | E5: =D5*1.1 -> 14552965 | F5: =E5*1.1 -> 16008261 | G5: =F5*1.1 -> 17609087
A6: Net Income | B6: =Sheet1!B6 -> 2988909 | C6: =Sheet1!C6 -> 2444253 | D6: =Sheet1!D6 -> 5437809 | E6: =E5*41.1% -> 5981268.5 | F6: =F5*41.1% -> 6579395.4 | G6: =G5*41.1% -> 7237334.9
A7: Operating Cash Flow | B7: =Sheet1!B10 -> 6336253 | C7: =Sheet1!C10 -> 4056906 | D7: =Sheet1!D10 -> 3481662 | E7: =E6*64% -> 3828011.9 | F7: =F6*64% -> 4210813 | G7: =G6*64% -> 4631894.4
A8: Capital Expenditure | B8: =Sheet1!B11 -> 235497 | C8: =Sheet1!C11 -> 224231 | D8: =Sheet1!D11 -> 61409 | E8: =D8*1.05 -> 64479.45 | F8: =E8*1.05 -> 67703.423 | G8: =F8*1.05 -> 71088.594
A9: Free Cash Flow | B9: =B7-B8 -> 6100756 | C9: =C7-C8 -> 3832675 | D9: =D7-D8 -> 3420253 | E9: =E7-E8 -> 3763532.4 | F9: =F7-F8 -> 4143109.6 | G9: =G7-G8 -> 4560805.8

Sheet DCF Valuation
A1: Particulars | B1: 2025E | C1: 2026E | D1: 2027E
A2: Free Cash Flow | B2: 3763532 | C2: 4143110 | D2: 4560806
A3: Discount Factor | B3: =1/(1+10%)^1 -> 0.90909091 | C3: =1/(1+10%)^2 -> 0.82644628 | D3: =1/(1+10%)^3 -> 0.7513148
A4: Present Value of FCF | B4: =B2*B3 -> 3421392.7 | C4: =C2*C3 -> 3424057.9 | D4: =D2*D3 -> 3426601.1
A5: Terminal Value | B5: — | C5: — | D5: =D2*(1+3%)/(10%-3%) -> 67109003
A6: Present Value of Terminal Value | B6: — | C6: — | D6: =D5*D3 -> 50419987
A7: Enterprise Value | B7: — | C7: — | D7: =SUM(B4:D4)+D6 -> 60692039
